eazyserver/__init__.py
eazyserver/cli.py
eazyserver/eazyserver.py
eazyserver/logger.conf
eazyserver/settings.ini
eazyserver/blueprints/__init__.py
eazyserver/blueprints/config.py
eazyserver/blueprints/healthz.py
eazyserver/blueprints/indexroute.py
eazyserver/blueprints/jsonrpc.py
eazyserver/core/__init__.py
eazyserver/core/behaviour_base.py
eazyserver/core/function_mapper.py
eazyserver/core/influxdb_connector.py
eazyserver/core/kafka_connector.py
eazyserver/core/utils.py
eazyserver/rpc/__init__.py
eazyserver/rpc/exceptions.py
eazyserver/rpc/influxdb_api.py
eazyserver/rpc/meta.py
eazyserver-0.2.7.dist-info/AUTHORS.rst
eazyserver-0.2.7.dist-info/LICENSE
eazyserver-0.2.7.dist-info/METADATA
eazyserver-0.2.7.dist-info/WHEEL
eazyserver-0.2.7.dist-info/entry_points.txt
eazyserver-0.2.7.dist-info/top_level.txt
eazyserver-0.2.7.dist-info/RECORD
