Metadata-Version: 2.1
Name: eazyserver
Version: 0.2.7
Summary: A simple python web framework for creating RESTful and JSON-RPC services
Home-page: https://github.com/ashutoshdtu/eazyserver
Author: Ashutosh Mishra
Author-email: ashutoshdtu@gmail.com
License: MIT license
Keywords: eazyserver
Platform: UNKNOWN
Classifier: Development Status :: 2 - Pre-Alpha
Classifier: Intended Audience :: Developers
Classifier: License :: OSI Approved :: MIT License
Classifier: Natural Language :: English
Classifier: Programming Language :: Python :: 2
Classifier: Programming Language :: Python :: 2.7
Classifier: Programming Language :: Python :: 3
Classifier: Programming Language :: Python :: 3.4
Classifier: Programming Language :: Python :: 3.5
Classifier: Programming Language :: Python :: 3.6
Classifier: Programming Language :: Python :: 3.7
Requires-Dist: bumpversion (==0.5.3)
Requires-Dist: wheel (==0.32.1)
Requires-Dist: watchdog (==0.9.0)
Requires-Dist: flake8 (==3.5.0)
Requires-Dist: tox (==3.5.2)
Requires-Dist: coverage (==4.5.1)
Requires-Dist: Sphinx (==1.8.1)
Requires-Dist: twine (==1.12.1)
Requires-Dist: Click (>=6.0)
Requires-Dist: eve (==0.8.1)
Requires-Dist: eve-swagger (==0.0.11)
Requires-Dist: flask (>=1.0)
Requires-Dist: python-socketio (==2.0.0)
Requires-Dist: flask-socketio (==3.0.1)
Requires-Dist: jsonrpcserver (==3.5.6)
Requires-Dist: marshmallow (==2.16.3)
Requires-Dist: gunicorn (==19.9.0)
Requires-Dist: flatten-json (==0.1.6)
Requires-Dist: influxdb (==5.0.0)
Requires-Dist: kafka-python (==1.4.4)
